repo_peek/__init__.py
repo_peek/cli.py
repo_peek/config.py
repo_peek/fetch.py
repo_peek/logging.py
repo_peek/main.py
repo_peek/utils.py
repo_peek-0.2.0.dist-info/entry_points.txt
repo_peek-0.2.0.dist-info/LICENSE
repo_peek-0.2.0.dist-info/WHEEL
repo_peek-0.2.0.dist-info/METADATA
repo_peek-0.2.0.dist-info/RECORD
