Metadata-Version: 2.1
Name: repo-peek
Version: 0.2.0
Summary: A command line tool to peek a remote repo locally.
License: MIT
Author: unrahul
Author-email: rahulunair@gmail.com
Requires-Python: >=3.7,<4.0
Classifier: License :: OSI Approved :: MIT License
Classifier: Programming Language :: Python :: 3
Classifier: Programming Language :: Python :: 3.7
Classifier: Programming Language :: Python :: 3.8
Classifier: Programming Language :: Python :: 3.9
Requires-Dist: aiofiles (>=0.6.0,<0.7.0)
Requires-Dist: aiohttp[speedups] (>=3.7.3,<4.0.0)
Requires-Dist: ciso8601 (>=2.1.3,<3.0.0)
Requires-Dist: loguru (>=0.5.3,<0.6.0)
Requires-Dist: sh (>=1.14.1,<2.0.0)
Requires-Dist: shellingham (>=1.4.0,<2.0.0)
Requires-Dist: typer (>=0.3.2,<0.4.0)
Project-URL: Documentation, https://github.com/rahulunair/github-peek
